src/__init__.py
src/api/__init__.py
src/api/dependencies.py
src/api/middleware.py
src/api/routes.py
src/cli/__init__.py
src/config/__init__.py
src/config/logging_config.py
src/config/settings.py
src/core/__init__.py
src/core/llm_processor.py
src/core/ocr_engine.py
src/core/pipeline.py
src/core/preprocessor.py
src/core/table_extractor.py
src/main.py
src/models/.gitkeep
src/models/__init__.py
src/models/invoice_schema.py
src/models/validation.py
src/prompts/__init__.py
src/prompts/extraction_prompts.py
src/prompts/templates/english.txt
src/prompts/templates/estonian.txt
src/prompts/templates/german.txt
src/utils/__init__.py
src/utils/file_utils.py
src/utils/image_utils.py
src/utils/monitoring.py
src/utils/text_utils.py
pocro-0.1.5.dist-info/LICENSE
pocro-0.1.5.dist-info/METADATA
pocro-0.1.5.dist-info/WHEEL
pocro-0.1.5.dist-info/entry_points.txt
pocro-0.1.5.dist-info/RECORD
