Metadata-Version: 2.3
Name: pocro
Version: 0.1.5
Summary: European Invoice OCR and Data Extraction Tool
License: MIT
Author: Your Name
Author-email: your.email@example.com
Requires-Python: >=3.10,<4.0
Classifier: License :: OSI Approved :: MIT License
Classifier: Programming Language :: Python :: 3
Classifier: Programming Language :: Python :: 3.10
Classifier: Programming Language :: Python :: 3.11
Classifier: Programming Language :: Python :: 3.12
Classifier: Programming Language :: Python :: 3.13
Requires-Dist: Pillow (==10.4.0)
Requires-Dist: PyMuPDF (==1.20.0)
Requires-Dist: accelerate (==0.24.1)
Requires-Dist: aiofiles (==23.2.1)
Requires-Dist: alembic (==1.12.1)
Requires-Dist: bitsandbytes (==0.41.2.post2)
Requires-Dist: click (==8.1.7)
Requires-Dist: easyocr (==1.7.0)
Requires-Dist: fastapi (==0.104.1)
Requires-Dist: loguru (==0.7.2)
Requires-Dist: numpy (>=1.26.0)
Requires-Dist: opencv-python (==4.6.0.66)
Requires-Dist: paddleocr (==2.7.0)
Requires-Dist: pandas (==2.3.0)
Requires-Dist: pdf2image (==1.16.3)
Requires-Dist: prometheus-client (==0.19.0)
Requires-Dist: psutil (==5.9.6)
Requires-Dist: pydantic (==1.10.13)
Requires-Dist: python-dotenv (==1.0.0)
Requires-Dist: python-multipart (==0.0.6)
Requires-Dist: redis (==5.0.1)
Requires-Dist: sqlalchemy (==2.0.23)
Requires-Dist: torch (==2.1.0)
Requires-Dist: torchvision (==0.16.0)
Requires-Dist: tqdm (==4.66.1)
Requires-Dist: transformers (==4.35.0)
Requires-Dist: uvicorn[standard] (==0.24.0)
